{
  "type": "minecraft:block",
  "pools": [
    {
      "rolls": 1.0,
      "entries": [
        {
          "type": "minecraft:item",
          "name": "roadworks:sign",
          "functions": [
            {
              "function": "minecraft:copy_nbt",
              "source": "block_entity",
              "ops": [
                {
                  "source": "sign_type",
                  "target": "BlockEntityTag.sign_type",
                  "op": "replace"
                }
              ]
            }
          ]
        }
      ]
    }
  ]
}

